{
	"last24h": [
		0.01666666753590107
	],
	"last60min": [
		0.0,
		0.0,
		0.0,
		0.0,
		0.0,
		0.0,
		0.0,
		0.0,
		0.0,
		0.0,
		0.0,
		0.0,
		0.0,
		0.0,
		0.0,
		0.0,
		0.0,
		0.0,
		0.0,
		0.0,
		0.0,
		0.0,
		0.0,
		0.0,
		0.0,
		0.0,
		0.0,
		0.0,
		0.0,
		0.0,
		0.0,
		0.0,
		0.0,
		0.0,
		0.0,
		0.0,
		0.0,
		0.0,
		0.0,
		0.0,
		0.0,
		0.0,
		0.0,
		0.0,
		0.0,
		0.0,
		0.0,
		0.0,
		0.0,
		0.0,
		0.0,
		0.0,
		0.0,
		0.0,
		0.0,
		0.0,
		0.0,
		0.0,
		0.0,
		1.0
	],
	"lastSamples": {
		"last24h": 3601,
		"last60min": 3601
	}
}